poetry_alias/__init__.py
poetry_alias/commands.py
poetry_alias/exceptions.py
poetry_alias/manager.py
poetry_alias/plugin.py
poetry_alias/tests/__init__.py
poetry_alias/tests/conftest.py
poetry_alias/tests/test_commands.py
poetry_alias/tests/test_exceptions.py
poetry_alias/tests/test_manager.py
poetry_alias/tests/test_plugin.py
poetry_alias-0.1.0.dist-info/entry_points.txt
poetry_alias-0.1.0.dist-info/LICENSE
poetry_alias-0.1.0.dist-info/WHEEL
poetry_alias-0.1.0.dist-info/METADATA
poetry_alias-0.1.0.dist-info/RECORD
