Metadata-Version: 2.1
Name: poetry-alias
Version: 0.1.0
Summary: Pew-style project management for Poetry
License: MIT
Author: Clemens Kaposi
Author-email: clemens.kaposi@obda.net
Requires-Python: >=3.7,<4.0
Classifier: License :: OSI Approved :: MIT License
Classifier: Programming Language :: Python :: 3
Classifier: Programming Language :: Python :: 3.10
Classifier: Programming Language :: Python :: 3.7
Classifier: Programming Language :: Python :: 3.8
Classifier: Programming Language :: Python :: 3.9
Requires-Dist: poetry (>=1.2.0a2,<2.0.0)
Requires-Dist: tomlkit (>=0.7.2,<0.8.0)
